array_xpl/__init__.py
array_xpl/array_xpl.py
array_xpl/eval_metrics.py
array_xpl/file_ops.py
array_xpl/plotter.py
array_xpl/utils.py
array_xpl-0.0.1.dist-info/METADATA
array_xpl-0.0.1.dist-info/WHEEL
array_xpl-0.0.1.dist-info/entry_points.txt
array_xpl-0.0.1.dist-info/top_level.txt
array_xpl-0.0.1.dist-info/RECORD
