Metadata-Version: 2.1
Name: array_xpl
Version: 0.0.1
Project-URL: Homepage, https://github.com/338rajesh/npi
Requires-Python: >=3.10.0
Requires-Dist: numpy==1.26.4
Requires-Dist: matplotlib==3.9.0
Requires-Dist: tqdm==4.66.4
Requires-Dist: tabulate==0.9.0
